{
  "type": "minecraft:entity",
  "pools": [
    {
      "rolls": 1,
      "entries": [
        {
          "type": "minecraft:item",
          "name": "minecraft:snowball",
          "functions": [
            {
              "function": "minecraft:set_name",
              "name": { "translate": "item.fartcraft.fart_in_a_bottle", "italic": false}
            },
			{
			  "function": "minecraft:set_lore",
			  "lore": [
				{"translate":"lore.fartcraft.added_by","color":"#663300","italic":false}
			  ]
			},
            {
              "function": "minecraft:set_nbt",
              "tag": "{CustomModelData:6420500,fartcraft:{id:\"fart_in_a_bottle\"}}"
            }
          ]
        }
      ]
    }
  ]
}